minos/aggregate/__init__.py
minos/aggregate/actions.py
minos/aggregate/aggregate.py
minos/aggregate/collections.py
minos/aggregate/contextvars.py
minos/aggregate/entities/__init__.py
minos/aggregate/entities/collections.py
minos/aggregate/entities/models.py
minos/aggregate/entities/refs/__init__.py
minos/aggregate/entities/refs/extractors.py
minos/aggregate/entities/refs/injectors.py
minos/aggregate/entities/refs/models.py
minos/aggregate/entities/refs/resolvers.py
minos/aggregate/events/__init__.py
minos/aggregate/events/entries.py
minos/aggregate/events/fields.py
minos/aggregate/events/models.py
minos/aggregate/events/repositories/__init__.py
minos/aggregate/events/repositories/abc.py
minos/aggregate/events/repositories/database/__init__.py
minos/aggregate/events/repositories/database/factories.py
minos/aggregate/events/repositories/database/impl.py
minos/aggregate/events/repositories/memory.py
minos/aggregate/exceptions.py
minos/aggregate/queries.py
minos/aggregate/snapshots/__init__.py
minos/aggregate/snapshots/entries.py
minos/aggregate/snapshots/repositories/__init__.py
minos/aggregate/snapshots/repositories/abc.py
minos/aggregate/snapshots/repositories/database/__init__.py
minos/aggregate/snapshots/repositories/database/factories.py
minos/aggregate/snapshots/repositories/database/impl.py
minos/aggregate/snapshots/repositories/memory.py
minos/aggregate/snapshots/services.py
minos/aggregate/testing/__init__.py
minos/aggregate/testing/events/__init__.py
minos/aggregate/testing/events/repositories/__init__.py
minos/aggregate/testing/events/repositories/factories.py
minos/aggregate/testing/events/repositories/testcases.py
minos/aggregate/testing/snapshots/__init__.py
minos/aggregate/testing/snapshots/repositories/__init__.py
minos/aggregate/testing/snapshots/repositories/factories.py
minos/aggregate/testing/snapshots/repositories/testcases.py
minos/aggregate/testing/transactions/__init__.py
minos/aggregate/testing/transactions/repositories/__init__.py
minos_microservice_aggregate-0.7.0.dist-info/LICENSE
minos_microservice_aggregate-0.7.0.dist-info/WHEEL
minos_microservice_aggregate-0.7.0.dist-info/METADATA
minos_microservice_aggregate-0.7.0.dist-info/RECORD
